polydev.github-0.1.3-py3.7-nspkg.pth
polydev/github/__init__.py
polydev/github/zest_hooks.py
polydev.github-0.1.3.dist-info/LICENSE
polydev.github-0.1.3.dist-info/METADATA
polydev.github-0.1.3.dist-info/WHEEL
polydev.github-0.1.3.dist-info/entry_points.txt
polydev.github-0.1.3.dist-info/namespace_packages.txt
polydev.github-0.1.3.dist-info/top_level.txt
polydev.github-0.1.3.dist-info/zip-safe
polydev.github-0.1.3.dist-info/RECORD
